health_tracking/__init__.py
health_tracking/constants.py
health_tracking/workouts.py
health_tracking-0.1.1.dist-info/AUTHORS.rst
health_tracking-0.1.1.dist-info/LICENSE.txt
health_tracking-0.1.1.dist-info/METADATA
health_tracking-0.1.1.dist-info/WHEEL
health_tracking-0.1.1.dist-info/top_level.txt
health_tracking-0.1.1.dist-info/RECORD
