Metadata-Version: 2.1
Name: health-tracking
Version: 0.1.1
Summary: Parse Apple Health App dump conveniently and create visualizations.
Home-page: https://github.com/se-jaeger/health-tracking
Author: Sebastian Jäger
Author-email: message@sebastian-jaeger.me
License: apache
Project-URL: Documentation, https://health-tracking.readthedocs.io/en/latest/
Platform: any
Classifier: Development Status :: 4 - Beta
Classifier: Programming Language :: Python
Requires-Python: >= 3.7
Requires-Dist: pandas
Requires-Dist: matplotlib
Requires-Dist: seaborn
Provides-Extra: testing
Requires-Dist: pytest ; extra == 'testing'
Requires-Dist: pytest-cov ; extra == 'testing'
